.bzrignore
NEWS.txt
README.txt
setup.py
setuptools_bzr/__init__.py
setuptools_bzr.egg-info/PKG-INFO
setuptools_bzr.egg-info/SOURCES.txt
setuptools_bzr.egg-info/dependency_links.txt
setuptools_bzr.egg-info/entry_points.txt
setuptools_bzr.egg-info/top_level.txt