Metadata-Version: 1.1
Name: setuptools-bzr
Version: 2.2
Summary: setuptools plugin for bzr
Home-page: https://launchpad.net/setuptoolsbzr
Author: Richard Gomes
Author-email: rgomes.info@gmail.com
License: LGPLv3
Keywords: distutils setuptools setup bzr bazaar
Platform: UNKNOWN
Classifier: Development Status :: 5 - Production/Stable
Classifier: Programming Language :: Python
Classifier: Programming Language :: Python :: 2
Classifier: Programming Language :: Python :: 2.4
Classifier: Programming Language :: Python :: 2.5
Classifier: Programming Language :: Python :: 2.6
Classifier: Programming Language :: Python :: 2.7
Classifier: Programming Language :: Python :: 3
Classifier: Programming Language :: Python :: 3.1
Classifier: Programming Language :: Python :: 3.2
Classifier: Programming Language :: Python :: 3.3
Classifier: Intended Audience :: Developers
Classifier: Operating System :: OS Independent
Classifier: License :: OSI Approved :: GNU Lesser General Public License v2 or later (LGPLv2+)
Classifier: Topic :: Software Development :: Version Control
Classifier: Framework :: Setuptools Plugin
